nonebot_plugin_flatter/__init__.py
nonebot_plugin_flatter-0.1.0.dist-info/LICENSE
nonebot_plugin_flatter-0.1.0.dist-info/WHEEL
nonebot_plugin_flatter-0.1.0.dist-info/METADATA
nonebot_plugin_flatter-0.1.0.dist-info/RECORD
