Metadata-Version: 2.1
Name: nonebot-plugin-flatter
Version: 0.1.0
Summary: Nonebot flatter plugin for QQ in Nonebot2
License: MIT
Author: Jerry080801
Author-email: jerry080801@outlook.com
Requires-Python: >=3.10,<4.0
Classifier: License :: OSI Approved :: MIT License
Classifier: Programming Language :: Python :: 3
Classifier: Programming Language :: Python :: 3.10
